README.rst
setup.py
Fabric_Alias.egg-info/PKG-INFO
Fabric_Alias.egg-info/SOURCES.txt
Fabric_Alias.egg-info/dependency_links.txt
Fabric_Alias.egg-info/requires.txt
Fabric_Alias.egg-info/top_level.txt
fabric_alias/__init__.py