Metadata-Version: 1.0
Name: Fabric-Alias
Version: 0.0.1
Summary: fabric_alias is a plugin for fabric when using fabfile.
Home-page: UNKNOWN
Author: Hiroyuki Ishii
Author-email: UNKNOWN
License: UNKNOWN
Platform: UNKNOWN
